[
  {
    "id": "clumsy_dash",
    "//": "A movement skill that you start with that will be removed once it hits max level",
    "type": "SPELL",
    "name": "Dash",
    "description": "You have heard rumours of being able to move light on your feet, perhaps you can try it yourself?",
    "message": "As you attempt to move quickly, you feel your feet become tangled and you trip loudly",
    "spell_class": "MARTIAL",
    "shape": "blast",
    "effect": "dash",
    "damage_type": "bash",
    "min_damage": 0,
    "max_damage": 0,
    "max_level": 1,
    "valid_targets": [ "ground" ],
    "flags": [ "NON_MAGICAL", "LOUD", "NO_HANDS" ],
    "base_casting_time": 150,
    "base_energy_cost": 200,
    "min_range": 1,
    "max_range": 1,
    "energy_source": "STAMINA"
  },
  {
    "id": "donkey_roll",
    "//": "You will not forget this ability once it hits max level",
    "type": "SPELL",
    "name": "Donkey Roll",
    "description": "You throw away any pride you have and dive across the ground",
    "message": "You shift your weight and inelegantly yet gracefully roll across the ground",
    "spell_class": "MARTIAL",
    "shape": "blast",
    "effect": "dash",
    "damage_type": "bash",
    "min_damage": 0,
    "max_damage": 0,
    "max_level": 5,
    "valid_targets": [ "ground" ],
    "flags": [ "NON_MAGICAL", "NO_HANDS" ],
    "base_casting_time": 100,
    "base_energy_cost": 50,
    "min_range": 1,
    "max_range": 2,
    "range_increment": 0.5,
    "energy_source": "STAMINA"
  },
  {
    "id": "wind_following_steps",
    "//": "",
    "type": "SPELL",
    "name": "Wind Following Steps",
    "description": "You channel energy into your feet and legs, making your movements flow with the wind",
    "message": "Your movements become smooth and natural",
    "spell_class": "QI",
    "shape": "blast",
    "effect": "effect_on_condition",
    "effect_str": "EOC_WIND_FOLLOWING_STEPS_START",
    "max_level": 10,
    "min_duration": { "math": [ "(u_spell_level('wind_following_steps') * 1000) + 5000" ] },
    "max_duration": { "math": [ "(u_spell_level('wind_following_steps') * 10000) + 10000" ] },
    "valid_targets": [ "self" ],
    "flags": [ "NON_MAGICAL", "NO_HANDS", "SILENT", "RANDOM_DURATION", "NO_FAIL" ],
    "base_casting_time": 100,
    "base_energy_cost": 150,
    "energy_source": { "type": "VITAMIN", "vitamin": "qi_vitamin", "color": "c_blue" }
  },
  {
    "id": "wuxia_three_needles",
    "type": "requirement",
    "//components": [ [ [ "bronze_nail", 3 ], [ "nail", 3 ] ] ],
    "components": [
      [
        [ "combatnail", 3 ],
        [ "needle_bone", 3 ],
        [ "needle_curved", 3 ],
        [ "needle_wood", 3 ],
        [ "needle_steel", 3 ],
        [ "syringe", 3 ],
        [ "bronze_nail", 3 ],
        [ "nail", 3 ]
      ]
    ]
  },
  {
    "id": "three_needles_draw_venom",
    "//": "",
    "type": "SPELL",
    "name": "Three Needles Draw Venom",
    "description": "Carefully insert needles to draw poison from your body",
    "message": "You insert needles across your chest to expel the poison in your body.",
    "spell_class": "QI",
    "shape": "blast",
    "effect": "effect_on_condition",
    "effect_str": "EOC_THREE_NEEDLES_DRAW_VENOM_START",
    "max_level": 10,
    "valid_targets": [ "self" ],
    "components": "wuxia_three_needles",
    "flags": [ "NON_MAGICAL", "NO_HANDS", "LOUD" ],
    "base_casting_time": 60000,
    "casting_time_increment": -5400,
    "final_casting_time": 6000,
    "base_energy_cost": 300,
    "energy_increment": -20,
    "final_energy_cost": 100,
    "energy_source": { "type": "VITAMIN", "vitamin": "qi_vitamin", "color": "c_blue" }
  },
  {
    "id": "soul_burning_meridian_reversal",
    "//": "Give huge buff for 5 minutes. After 1 minute side effects start kicking in. After the 5 minutes, 1 day penalty",
    "///": "You will probably die",
    "type": "SPELL",
    "name": "Soul Burning Meridian Reversal",
    "description": "Burn your soul, and reverse you qi. Your death will arrive soon.",
    "message": "You raise your hand, wondering if these will be your final moments.",
    "spell_class": "QI",
    "shape": "blast",
    "effect": "effect_on_condition",
    "effect_str": "EOC_SOUL_BURNING_MERIDIAN_REVERSAL_CONFIRM",
    "max_level": 0,
    "valid_targets": [ "self" ],
    "flags": [ "NON_MAGICAL", "NO_HANDS", "LOUD", "NO_FAIL" ],
    "base_casting_time": 50,
    "base_energy_cost": 0,
    "energy_source": { "type": "VITAMIN", "vitamin": "qi_vitamin", "color": "c_blue" }
  }
]
